MANIFEST.in
README.rst
setup.py
dbc/__init__.py
dbc/dbc.py
dbc/main.py
dbc/utils.py
dropbox_cli.egg-info/PKG-INFO
dropbox_cli.egg-info/SOURCES.txt
dropbox_cli.egg-info/dependency_links.txt
dropbox_cli.egg-info/entry_points.txt
dropbox_cli.egg-info/requires.txt
dropbox_cli.egg-info/top_level.txt