Metadata-Version: 1.0
Name: dropbox-cli
Version: 0.00.01
Summary: cli to manage your dropbox account 
Home-page: http://github.com/timofurrer/dropbox-cli
Author: Timo Furrer
Author-email: tuxtimo@gmail.com
License: UNKNOWN
Platform: UNKNOWN
